{
  "name": "topdown-objects",
  "description": "Object definitions for topdown game using Sprout Lands assets",
  "objects": {
    "chest": {
      "imagePath": "/assets/Sprout Lands - Sprites - Basic pack/Objects/Chest.png",
      "tileX": 0,
      "tileY": 0,
      "tileSize": 16
    },
    "tree": {
      "imagePath": "/assets/Sprout Lands - Sprites - Basic pack/Objects/Basic_Grass_Biom_things.png",
      "tileX": 2,
      "tileY": 0,
      "tileSize": 16
    },
    "rock": {
      "imagePath": "/assets/Sprout Lands - Sprites - Basic pack/Objects/Basic_Grass_Biom_things.png",
      "tileX": 3,
      "tileY": 0,
      "tileSize": 16
    },
    "flower": {
      "imagePath": "/assets/Sprout Lands - Sprites - Basic pack/Objects/Basic_Plants.png",
      "tileX": 0,
      "tileY": 0,
      "tileSize": 16
    },
    "bush": {
      "imagePath": "/assets/Sprout Lands - Sprites - Basic pack/Objects/Basic_Plants.png",
      "tileX": 1,
      "tileY": 0,
      "tileSize": 16
    },
    "egg": {
      "imagePath": "/assets/Sprout Lands - Sprites - Basic pack/Objects/Egg_item.png",
      "tileX": 0,
      "tileY": 0,
      "tileSize": 16
    },
    "milk": {
      "imagePath": "/assets/Sprout Lands - Sprites - Basic pack/Objects/Simple_Milk_and_grass_item.png",
      "tileX": 0,
      "tileY": 0,
      "tileSize": 16
    }
  }
}
